README.md
setup.cfg
setup.py
gp_distributions/Binomialdistribution.py
gp_distributions/Gaussiandistribution.py
gp_distributions/Generaldistribution.py
gp_distributions/__init__.py
gp_distributions.egg-info/PKG-INFO
gp_distributions.egg-info/SOURCES.txt
gp_distributions.egg-info/dependency_links.txt
gp_distributions.egg-info/not-zip-safe
gp_distributions.egg-info/top_level.txt